__init__.py
ingest_data.py
score.py
train.py
housing_tiger_2022-0.0.1.dist-info/LICENSE
housing_tiger_2022-0.0.1.dist-info/METADATA
housing_tiger_2022-0.0.1.dist-info/WHEEL
housing_tiger_2022-0.0.1.dist-info/top_level.txt
housing_tiger_2022-0.0.1.dist-info/RECORD
