Metadata-Version: 2.1
Name: housing-tiger-2022
Version: 0.0.1
Summary: A small example package
Author-email: "devaraj.saravana" <devaraj.saravana@tigeranaytics.com>
License: Copyright (c) 2018 The Python Packaging Authority        
Project-URL: Homepage, https://github.com/devaraj-saravana/pypi
Classifier: Programming Language :: Python :: 3
Classifier: License :: OSI Approved :: MIT License
Classifier: Operating System :: OS Independent
Requires-Python: >=3.7
License-File: LICENSE
